abc/__init__.py
zhushengwen-1.0.4.dist-info/DESCRIPTION.rst
zhushengwen-1.0.4.dist-info/METADATA
zhushengwen-1.0.4.dist-info/metadata.json
zhushengwen-1.0.4.dist-info/RECORD
zhushengwen-1.0.4.dist-info/top_level.txt
zhushengwen-1.0.4.dist-info/WHEEL
zhushengwen-1.0.4.dist-info/zip-safe
